hdr_sdk/__init__.py
hdr_sdk/anthropic.py
hdr_sdk/computer.py
hdr_sdk/exceptions.py
hdr_sdk/models/__init__.py
hdr_sdk/models/config.py
hdr_sdk/models/exceptions.py
hdr_sdk/schemas/__init__.py
hdr_sdk/schemas/action.py
hdr_sdk/schemas/bash_action.py
hdr_sdk/schemas/computer_actions.py
hdr_sdk/schemas/config.py
hdr_sdk/schemas/edit_actions.py
hdr_sdk/schemas/tool_base.py
hdr_sdk/tools/__init__.py
hdr_sdk/tools/computer_tools.py
hdr_sdk-0.1.0.dist-info/METADATA
hdr_sdk-0.1.0.dist-info/WHEEL
hdr_sdk-0.1.0.dist-info/licenses/LICENSE
hdr_sdk-0.1.0.dist-info/RECORD
