Metadata-Version: 2.4
Name: hdr-sdk
Version: 0.1.0
Summary: The computer use SDK from HDR
Project-URL: Homepage, https://hdr.is
Project-URL: Repository, https://github.com/hdresearch/hdr-sdk.git
Project-URL: Issues, https://github.com/hdresearch/hdr-sdk/issues
Project-URL: Github, https://github.com/hdresearch/hdr-sdk
Author-email: Tynan Daly <tynan.daly@hdr.is>
License-Expression: MIT
License-File: LICENSE
Keywords: python
Classifier: Intended Audience :: Developers
Classifier: Programming Language :: Python
Classifier: Programming Language :: Python :: 3
Classifier: Programming Language :: Python :: 3.9
Classifier: Programming Language :: Python :: 3.10
Classifier: Programming Language :: Python :: 3.11
Classifier: Programming Language :: Python :: 3.12
Classifier: Programming Language :: Python :: 3.13
Classifier: Topic :: Software Development :: Libraries :: Python Modules
Requires-Python: <4.0,>=3.10
Requires-Dist: anthropic>=0.42.0
Requires-Dist: pydantic>=2.10.3
Requires-Dist: python-dotenv>=1.0.1
Requires-Dist: rich>=13.9.4
Requires-Dist: structlog>=24.4.0
Requires-Dist: websockets>=14.1
